{
  "boxscore": {
    "teams": [
      {
        "team": {
          "id": "85",
          "uid": "s:40~l:54~t:85",
          "slug": "iupui-jaguars",
          "location": "IUPUI",
          "name": "Jaguars",
          "abbreviation": "IUPU",
          "displayName": "IUPUI Jaguars",
          "shortDisplayName": "IUPUI",
          "color": "A81F30",
          "alternateColor": "d59f0f",
          "logo": "https://a.espncdn.com/i/teamlogos/ncaa/500/85.png"
        },
        "statistics": []
      },
      {
        "team": {
          "id": "2473",
          "uid": "s:40~l:54~t:2473",
          "slug": "oakland-golden-grizzlies",
          "location": "Oakland",
          "name": "Golden Grizzlies",
          "abbreviation": "OAK",
          "displayName": "Oakland Golden Grizzlies",
          "shortDisplayName": "Oakland",
          "color": "04091c",
          "alternateColor": "bc955c",
          "logo": "https://a.espncdn.com/i/teamlogos/ncaa/500/2473.png"
        },
        "statistics": []
      }
    ],
    "players": [
      {
        "team": {
          "id": "85",
          "uid": "s:40~l:54~t:85",
          "slug": "iupui-jaguars",
          "location": "IUPUI",
          "name": "Jaguars",
          "abbreviation": "IUPU",
          "displayName": "IUPUI Jaguars",
          "shortDisplayName": "IUPUI",
          "color": "A81F30",
          "alternateColor": "d59f0f",
          "logo": "https://a.espncdn.com/i/teamlogos/ncaa/500/85.png"
        },
        "statistics": [
          {
            "names": [
              "MIN",
              "FG",
              "3PT",
              "FT",
              "OREB",
              "DREB",
              "REB",
              "AST",
              "STL",
              "BLK",
              "TO",
              "PF",
              "PTS"
            ],
            "keys": [
              "minutes",
              "fieldGoalsMade-fieldGoalsAttempted",
              "threePointFieldGoalsMade-threePointFieldGoalsAttempted",
              "freeThrowsMade-freeThrowsAttempted",
              "offensiveRebounds",
              "defensiveRebounds",
              "rebounds",
              "assists",
              "steals",
              "blocks",
              "turnovers",
              "fouls",
              "points"
            ],
            "labels": [
              "MIN",
              "FG",
              "3PT",
              "FT",
              "OREB",
              "DREB",
              "REB",
              "AST",
              "STL",
              "BLK",
              "TO",
              "PF",
              "PTS"
            ],
            "descriptions": [
              "Minutes",
              "Field Goals Made/Attempted",
              "3-Point Field Goals Made/Attempted",
              "Free Throws Made/Attempted",
              "Offensive Rebounds",
              "Defensive Rebounds",
              "Rebounds",
              "Assists",
              "Steals",
              "Blocks",
              "Turnovers",
              "Personal Fouls",
              "Points"
            ],
            "athletes": [
              {
                "active": true,
                "athlete": {
                  "id": "7159",
                  "uid": "s:40~l:54~a:7159",
                  "guid": "1e965b79ab0833ae6565c5c677dbf654",
                  "displayName": "Jernisha Cann",
                  "shortName": "J. Cann",
                  "links": [
                    {
                      "rel": [
                        "playercard",
                        "desktop",
                        "athlete"
                      ],
                      "href": "https://www.espn.com/womens-college-basketball/player/_/id/7159/jernisha-cann",
                      "text": "Player Card"
                    },
                    {
                      "rel": [
                        "stats",
                        "desktop",
                        "athlete"
                      ],
                      "href": "http://www.espn.com/womens-college-basketball/player/stats/_/id/7159/jernisha-cann",
                      "text": "Stats"
                    },
                    {
                      "rel": [
                        "gamelog",
                        "desktop",
                        "athlete"
                      ],
                      "href": "http://www.espn.com/womens-college-basketball/player/gamelog/_/id/7159/jernisha-cann",
                      "text": "Game Log"
                    },
                    {
                      "rel": [
                        "news",
                        "desktop",
                        "athlete"
                      ],
                      "href": "http://www.espn.com/womens-college-basketball/player/news/_/id/7159/jernisha-cann",
                      "text": "News"
                    },
                    {
                      "rel": [
                        "bio",
                        "desktop",
                        "athlete"
                      ],
                      "href": "http://www.espn.com/womens-college-basketball/player/bio/_/id/7159/jernisha-cann",
                      "text": "Bio"
                    },
                    {
                      "rel": [
                        "overview",
                        "desktop",
                        "athlete"
                      ],
                      "href": "http://www.espn.com/womens-college-basketball/player/_/id/7159/jernisha-cann",
                      "text": "Overview"
                    }
                  ],
                  "position": {
                    "name": "Forward",
                    "displayName": "Forward",
                    "abbreviation": "F"
                  }
                },
                "starter": true,
                "didNotPlay": true,
                "ejected": false,
                "stats": []
              },
              {
                "active": true,
                "athlete": {
                  "id": "7160",
                  "uid": "s:40~l:54~a:7160",
                  "guid": "c0058dc7f92c6f08819e87791e785c41",
                  "displayName": "Julia Whitted",
                  "shortName": "J. Whitted",
                  "links": [
                    {
                      "rel": [
                        "playercard",
                        "desktop",
                        "athlete"
                      ],
                      "href": "https://www.espn.com/womens-college-basketball/player/_/id/7160/julia-whitted",
                      "text": "Player Card"
                    },
                    {
                      "rel": [
                        "stats",
                        "desktop",
                        "athlete"
                      ],
                      "href": "http://www.espn.com/womens-college-basketball/player/stats/_/id/7160/julia-whitted",
                      "text": "Stats"
                    },
                    {
                      "rel": [
                        "gamelog",
                        "desktop",
                        "athlete"
                      ],
                      "href": "http://www.espn.com/womens-college-basketball/player/gamelog/_/id/7160/julia-whitted",
                      "text": "Game Log"
                    },
                    {
                      "rel": [
                        "news",
                        "desktop",
                        "athlete"
                      ],
                      "href": "http://www.espn.com/womens-college-basketball/player/news/_/id/7160/julia-whitted",
                      "text": "News"
                    },
                    {
                      "rel": [
                        "bio",
                        "desktop",
                        "athlete"
                      ],
                      "href": "http://www.espn.com/womens-college-basketball/player/bio/_/id/7160/julia-whitted",
                      "text": "Bio"
                    },
                    {
                      "rel": [
                        "overview",
                        "desktop",
                        "athlete"
                      ],
                      "href": "http://www.espn.com/womens-college-basketball/player/_/id/7160/julia-whitted",
                      "text": "Overview"
                    }
                  ],
                  "position": {
                    "name": "Center",
                    "displayName": "Center",
                    "abbreviation": "C"
                  }
                },
                "starter": true,
                "didNotPlay": true,
                "ejected": false,
                "stats": []
              },
              {
                "active": true,
                "athlete": {
                  "id": "7163",
                  "uid": "s:40~l:54~a:7163",
                  "guid": "7bc4297e522c439cbdcf1492631e50e8",
                  "displayName": "Ashley Conner",
                  "shortName": "A. Conner",
                  "links": [
                    {
                      "rel": [
                        "playercard",
                        "desktop",
                        "athlete"
                      ],
                      "href": "https://www.espn.com/womens-college-basketball/player/_/id/7163/ashley-conner",
                      "text": "Player Card"
                    },
                    {
                      "rel": [
                        "stats",
                        "desktop",
                        "athlete"
                      ],
                      "href": "http://www.espn.com/womens-college-basketball/player/stats/_/id/7163/ashley-conner",
                      "text": "Stats"
                    },
                    {
                      "rel": [
                        "gamelog",
                        "desktop",
                        "athlete"
                      ],
                      "href": "http://www.espn.com/womens-college-basketball/player/gamelog/_/id/7163/ashley-conner",
                      "text": "Game Log"
                    },
                    {
                      "rel": [
                        "news",
                        "desktop",
                        "athlete"
                      ],
                      "href": "http://www.espn.com/womens-college-basketball/player/news/_/id/7163/ashley-conner",
                      "text": "News"
                    },
                    {
                      "rel": [
                        "bio",
                        "desktop",
                        "athlete"
                      ],
                      "href": "http://www.espn.com/womens-college-basketball/player/bio/_/id/7163/ashley-conner",
                      "text": "Bio"
                    },
                    {
                      "rel": [
                        "overview",
                        "desktop",
                        "athlete"
                      ],
                      "href": "http://www.espn.com/womens-college-basketball/player/_/id/7163/ashley-conner",
                      "text": "Overview"
                    }
                  ],
                  "position": {
                    "name": "Not Available",
                    "displayName": "Not Available",
                    "abbreviation": "NA"
                  }
                },
                "starter": true,
                "didNotPlay": true,
                "ejected": false,
                "stats": []
              },
              {
                "active": true,
                "athlete": {
                  "id": "7162",
                  "uid": "s:40~l:54~a:7162",
                  "guid": "0d5acb7e90e7988fcdaa22cc160e3dcf",
                  "displayName": "Amy Cook",
                  "shortName": "A. Cook",
                  "links": [
                    {
                      "rel": [
                        "playercard",
                        "desktop",
                        "athlete"
                      ],
                      "href": "https://www.espn.com/womens-college-basketball/player/_/id/7162/amy-cook",
                      "text": "Player Card"
                    },
                    {
                      "rel": [
                        "stats",
                        "desktop",
                        "athlete"
                      ],
                      "href": "http://www.espn.com/womens-college-basketball/player/stats/_/id/7162/amy-cook",
                      "text": "Stats"
                    },
                    {
                      "rel": [
                        "gamelog",
                        "desktop",
                        "athlete"
                      ],
                      "href": "http://www.espn.com/womens-college-basketball/player/gamelog/_/id/7162/amy-cook",
                      "text": "Game Log"
                    },
                    {
                      "rel": [
                        "news",
                        "desktop",
                        "athlete"
                      ],
                      "href": "http://www.espn.com/womens-college-basketball/player/news/_/id/7162/amy-cook",
                      "text": "News"
                    },
                    {
                      "rel": [
                        "bio",
                        "desktop",
                        "athlete"
                      ],
                      "href": "http://www.espn.com/womens-college-basketball/player/bio/_/id/7162/amy-cook",
                      "text": "Bio"
                    },
                    {
                      "rel": [
                        "overview",
                        "desktop",
                        "athlete"
                      ],
                      "href": "http://www.espn.com/womens-college-basketball/player/_/id/7162/amy-cook",
                      "text": "Overview"
                    }
                  ],
                  "position": {
                    "name": "Not Available",
                    "displayName": "Not Available",
                    "abbreviation": "NA"
                  }
                },
                "starter": true,
                "didNotPlay": true,
                "ejected": false,
                "stats": []
              },
              {
                "active": true,
                "athlete": {
                  "id": "7161",
                  "uid": "s:40~l:54~a:7161",
                  "guid": "098ca42f3e96a9ef3b96363c714f0c0b",
                  "displayName": "Alicia Booyer",
                  "shortName": "A. Booyer",
                  "links": [
                    {
                      "rel": [
                        "playercard",
                        "desktop",
                        "athlete"
                      ],
                      "href": "https://www.espn.com/womens-college-basketball/player/_/id/7161/alicia-booyer",
                      "text": "Player Card"
                    },
                    {
                      "rel": [
                        "stats",
                        "desktop",
                        "athlete"
                      ],
                      "href": "http://www.espn.com/womens-college-basketball/player/stats/_/id/7161/alicia-booyer",
                      "text": "Stats"
                    },
                    {
                      "rel": [
                        "gamelog",
                        "desktop",
                        "athlete"
                      ],
                      "href": "http://www.espn.com/womens-college-basketball/player/gamelog/_/id/7161/alicia-booyer",
                      "text": "Game Log"
                    },
                    {
                      "rel": [
                        "news",
                        "desktop",
                        "athlete"
                      ],
                      "href": "http://www.espn.com/womens-college-basketball/player/news/_/id/7161/alicia-booyer",
                      "text": "News"
                    },
                    {
                      "rel": [
                        "bio",
                        "desktop",
                        "athlete"
                      ],
                      "href": "http://www.espn.com/womens-college-basketball/player/bio/_/id/7161/alicia-booyer",
                      "text": "Bio"
                    },
                    {
                      "rel": [
                        "overview",
                        "desktop",
                        "athlete"
                      ],
                      "href": "http://www.espn.com/womens-college-basketball/player/_/id/7161/alicia-booyer",
                      "text": "Overview"
                    }
                  ],
                  "position": {
                    "name": "Not Available",
                    "displayName": "Not Available",
                    "abbreviation": "NA"
                  }
                },
                "starter": true,
                "didNotPlay": true,
                "ejected": false,
                "stats": []
              }
            ],
            "totals": [
              "",
              "-----",
              "-----",
              "-----",
              "--",
              "--",
              "--",
              "--",
              "--",
              "--",
              "--",
              "--",
              "--"
            ]
          }
        ]
      },
      {
        "team": {
          "id": "2473",
          "uid": "s:40~l:54~t:2473",
          "slug": "oakland-golden-grizzlies",
          "location": "Oakland",
          "name": "Golden Grizzlies",
          "abbreviation": "OAK",
          "displayName": "Oakland Golden Grizzlies",
          "shortDisplayName": "Oakland",
          "color": "04091c",
          "alternateColor": "bc955c",
          "logo": "https://a.espncdn.com/i/teamlogos/ncaa/500/2473.png"
        },
        "statistics": [
          {
            "names": [
              "MIN",
              "FG",
              "3PT",
              "FT",
              "OREB",
              "DREB",
              "REB",
              "AST",
              "STL",
              "BLK",
              "TO",
              "PF",
              "PTS"
            ],
            "keys": [
              "minutes",
              "fieldGoalsMade-fieldGoalsAttempted",
              "threePointFieldGoalsMade-threePointFieldGoalsAttempted",
              "freeThrowsMade-freeThrowsAttempted",
              "offensiveRebounds",
              "defensiveRebounds",
              "rebounds",
              "assists",
              "steals",
              "blocks",
              "turnovers",
              "fouls",
              "points"
            ],
            "labels": [
              "MIN",
              "FG",
              "3PT",
              "FT",
              "OREB",
              "DREB",
              "REB",
              "AST",
              "STL",
              "BLK",
              "TO",
              "PF",
              "PTS"
            ],
            "descriptions": [
              "Minutes",
              "Field Goals Made/Attempted",
              "3-Point Field Goals Made/Attempted",
              "Free Throws Made/Attempted",
              "Offensive Rebounds",
              "Defensive Rebounds",
              "Rebounds",
              "Assists",
              "Steals",
              "Blocks",
              "Turnovers",
              "Personal Fouls",
              "Points"
            ],
            "athletes": [
              {
                "active": true,
                "athlete": {
                  "id": "5993",
                  "uid": "s:40~l:54~a:5993",
                  "guid": "8d97f00d5f0e9c7a8d0fedd85385f45a",
                  "displayName": "Hanna Reising",
                  "shortName": "H. Reising",
                  "links": [
                    {
                      "rel": [
                        "playercard",
                        "desktop",
                        "athlete"
                      ],
                      "href": "https://www.espn.com/womens-college-basketball/player/_/id/5993/hanna-reising",
                      "text": "Player Card"
                    },
                    {
                      "rel": [
                        "stats",
                        "desktop",
                        "athlete"
                      ],
                      "href": "http://www.espn.com/womens-college-basketball/player/stats/_/id/5993/hanna-reising",
                      "text": "Stats"
                    },
                    {
                      "rel": [
                        "gamelog",
                        "desktop",
                        "athlete"
                      ],
                      "href": "http://www.espn.com/womens-college-basketball/player/gamelog/_/id/5993/hanna-reising",
                      "text": "Game Log"
                    },
                    {
                      "rel": [
                        "news",
                        "desktop",
                        "athlete"
                      ],
                      "href": "http://www.espn.com/womens-college-basketball/player/news/_/id/5993/hanna-reising",
                      "text": "News"
                    },
                    {
                      "rel": [
                        "bio",
                        "desktop",
                        "athlete"
                      ],
                      "href": "http://www.espn.com/womens-college-basketball/player/bio/_/id/5993/hanna-reising",
                      "text": "Bio"
                    },
                    {
                      "rel": [
                        "overview",
                        "desktop",
                        "athlete"
                      ],
                      "href": "http://www.espn.com/womens-college-basketball/player/_/id/5993/hanna-reising",
                      "text": "Overview"
                    }
                  ],
                  "jersey": "32 ",
                  "position": {
                    "name": "Forward",
                    "displayName": "Forward",
                    "abbreviation": "F"
                  }
                },
                "starter": true,
                "didNotPlay": true,
                "ejected": false,
                "stats": []
              },
              {
                "active": true,
                "athlete": {
                  "id": "5616",
                  "uid": "s:40~l:54~a:5616",
                  "guid": "3fb83fa940b79ac6a11e983f562055e2",
                  "displayName": "Riikka Terava",
                  "shortName": "R. Terava",
                  "links": [
                    {
                      "rel": [
                        "playercard",
                        "desktop",
                        "athlete"
                      ],
                      "href": "https://www.espn.com/womens-college-basketball/player/_/id/5616/riikka-terava",
                      "text": "Player Card"
                    },
                    {
                      "rel": [
                        "stats",
                        "desktop",
                        "athlete"
                      ],
                      "href": "http://www.espn.com/womens-college-basketball/player/stats/_/id/5616/riikka-terava",
                      "text": "Stats"
                    },
                    {
                      "rel": [
                        "gamelog",
                        "desktop",
                        "athlete"
                      ],
                      "href": "http://www.espn.com/womens-college-basketball/player/gamelog/_/id/5616/riikka-terava",
                      "text": "Game Log"
                    },
                    {
                      "rel": [
                        "news",
                        "desktop",
                        "athlete"
                      ],
                      "href": "http://www.espn.com/womens-college-basketball/player/news/_/id/5616/riikka-terava",
                      "text": "News"
                    },
                    {
                      "rel": [
                        "bio",
                        "desktop",
                        "athlete"
                      ],
                      "href": "http://www.espn.com/womens-college-basketball/player/bio/_/id/5616/riikka-terava",
                      "text": "Bio"
                    },
                    {
                      "rel": [
                        "overview",
                        "desktop",
                        "athlete"
                      ],
                      "href": "http://www.espn.com/womens-college-basketball/player/_/id/5616/riikka-terava",
                      "text": "Overview"
                    }
                  ],
                  "jersey": "20 ",
                  "position": {
                    "name": "Guard",
                    "displayName": "Guard",
                    "abbreviation": "G"
                  }
                },
                "starter": true,
                "didNotPlay": true,
                "ejected": false,
                "stats": []
              },
              {
                "active": true,
                "athlete": {
                  "id": "5614",
                  "uid": "s:40~l:54~a:5614",
                  "guid": "98fea901e21ce5a19fef99c3aaca1433",
                  "displayName": "Jessica Pike",
                  "shortName": "J. Pike",
                  "links": [
                    {
                      "rel": [
                        "playercard",
                        "desktop",
                        "athlete"
                      ],
                      "href": "https://www.espn.com/womens-college-basketball/player/_/id/5614/jessica-pike",
                      "text": "Player Card"
                    },
                    {
                      "rel": [
                        "stats",
                        "desktop",
                        "athlete"
                      ],
                      "href": "http://www.espn.com/womens-college-basketball/player/stats/_/id/5614/jessica-pike",
                      "text": "Stats"
                    },
                    {
                      "rel": [
                        "gamelog",
                        "desktop",
                        "athlete"
                      ],
                      "href": "http://www.espn.com/womens-college-basketball/player/gamelog/_/id/5614/jessica-pike",
                      "text": "Game Log"
                    },
                    {
                      "rel": [
                        "news",
                        "desktop",
                        "athlete"
                      ],
                      "href": "http://www.espn.com/womens-college-basketball/player/news/_/id/5614/jessica-pike",
                      "text": "News"
                    },
                    {
                      "rel": [
                        "bio",
                        "desktop",
                        "athlete"
                      ],
                      "href": "http://www.espn.com/womens-college-basketball/player/bio/_/id/5614/jessica-pike",
                      "text": "Bio"
                    },
                    {
                      "rel": [
                        "overview",
                        "desktop",
                        "athlete"
                      ],
                      "href": "http://www.espn.com/womens-college-basketball/player/_/id/5614/jessica-pike",
                      "text": "Overview"
                    }
                  ],
                  "jersey": "4  ",
                  "position": {
                    "name": "Guard",
                    "displayName": "Guard",
                    "abbreviation": "G"
                  }
                },
                "starter": true,
                "didNotPlay": true,
                "ejected": false,
                "stats": []
              },
              {
                "active": true,
                "athlete": {
                  "id": "5608",
                  "uid": "s:40~l:54~a:5608",
                  "guid": "cbad1c4c959c26a88d4ef7c0061890df",
                  "displayName": "Bonnie Baker",
                  "shortName": "B. Baker",
                  "links": [
                    {
                      "rel": [
                        "playercard",
                        "desktop",
                        "athlete"
                      ],
                      "href": "https://www.espn.com/womens-college-basketball/player/_/id/5608/bonnie-baker",
                      "text": "Player Card"
                    },
                    {
                      "rel": [
                        "stats",
                        "desktop",
                        "athlete"
                      ],
                      "href": "http://www.espn.com/womens-college-basketball/player/stats/_/id/5608/bonnie-baker",
                      "text": "Stats"
                    },
                    {
                      "rel": [
                        "gamelog",
                        "desktop",
                        "athlete"
                      ],
                      "href": "http://www.espn.com/womens-college-basketball/player/gamelog/_/id/5608/bonnie-baker",
                      "text": "Game Log"
                    },
                    {
                      "rel": [
                        "news",
                        "desktop",
                        "athlete"
                      ],
                      "href": "http://www.espn.com/womens-college-basketball/player/news/_/id/5608/bonnie-baker",
                      "text": "News"
                    },
                    {
                      "rel": [
                        "bio",
                        "desktop",
                        "athlete"
                      ],
                      "href": "http://www.espn.com/womens-college-basketball/player/bio/_/id/5608/bonnie-baker",
                      "text": "Bio"
                    },
                    {
                      "rel": [
                        "overview",
                        "desktop",
                        "athlete"
                      ],
                      "href": "http://www.espn.com/womens-college-basketball/player/_/id/5608/bonnie-baker",
                      "text": "Overview"
                    }
                  ],
                  "position": {
                    "name": "Not Available",
                    "displayName": "Not Available",
                    "abbreviation": "NA"
                  }
                },
                "starter": true,
                "didNotPlay": true,
                "ejected": false,
                "stats": []
              },
              {
                "active": true,
                "athlete": {
                  "id": "5607",
                  "uid": "s:40~l:54~a:5607",
                  "guid": "f582cd235cc49ae34820220088419f78",
                  "displayName": "Nicole Piggott",
                  "shortName": "N. Piggott",
                  "links": [
                    {
                      "rel": [
                        "playercard",
                        "desktop",
                        "athlete"
                      ],
                      "href": "https://www.espn.com/womens-college-basketball/player/_/id/5607/nicole-piggott",
                      "text": "Player Card"
                    },
                    {
                      "rel": [
                        "stats",
                        "desktop",
                        "athlete"
                      ],
                      "href": "http://www.espn.com/womens-college-basketball/player/stats/_/id/5607/nicole-piggott",
                      "text": "Stats"
                    },
                    {
                      "rel": [
                        "gamelog",
                        "desktop",
                        "athlete"
                      ],
                      "href": "http://www.espn.com/womens-college-basketball/player/gamelog/_/id/5607/nicole-piggott",
                      "text": "Game Log"
                    },
                    {
                      "rel": [
                        "news",
                        "desktop",
                        "athlete"
                      ],
                      "href": "http://www.espn.com/womens-college-basketball/player/news/_/id/5607/nicole-piggott",
                      "text": "News"
                    },
                    {
                      "rel": [
                        "bio",
                        "desktop",
                        "athlete"
                      ],
                      "href": "http://www.espn.com/womens-college-basketball/player/bio/_/id/5607/nicole-piggott",
                      "text": "Bio"
                    },
                    {
                      "rel": [
                        "overview",
                        "desktop",
                        "athlete"
                      ],
                      "href": "http://www.espn.com/womens-college-basketball/player/_/id/5607/nicole-piggott",
                      "text": "Overview"
                    }
                  ],
                  "position": {
                    "name": "Not Available",
                    "displayName": "Not Available",
                    "abbreviation": "NA"
                  }
                },
                "starter": true,
                "didNotPlay": true,
                "ejected": false,
                "stats": []
              }
            ],
            "totals": [
              "",
              "-----",
              "-----",
              "-----",
              "--",
              "--",
              "--",
              "--",
              "--",
              "--",
              "--",
              "--",
              "--"
            ]
          }
        ]
      }
    ]
  },
  "format": {
    "regulation": {
      "periods": 2,
      "displayName": "Half",
      "slug": "half",
      "clock": 1200.0
    },
    "overtime": {
      "clock": 300.0
    }
  },
  "gameInfo": {
    "attendance": 0
  },
  "leaders": [
    {
      "team": {
        "id": "2473",
        "uid": "s:40~l:54~t:2473",
        "displayName": "Oakland Golden Grizzlies",
        "abbreviation": "OAK",
        "links": [
          {
            "href": "http://www.espn.com/womens-college-basketball/team/_/id/2473/oakland-golden-grizzlies",
            "text": "Clubhouse"
          },
          {
            "href": "http://www.espn.com/womens-college-basketball/team/schedule/_/id/2473",
            "text": "Schedule"
          }
        ],
        "logo": "https://a.espncdn.com/i/teamlogos/ncaa/500/2473.png"
      },
      "leaders": []
    },
    {
      "team": {
        "id": "85",
        "uid": "s:40~l:54~t:85",
        "displayName": "IUPUI Jaguars",
        "abbreviation": "IUPU",
        "links": [
          {
            "href": "http://www.espn.com/womens-college-basketball/team/_/id/85/iupui-jaguars",
            "text": "Clubhouse"
          },
          {
            "href": "http://www.espn.com/womens-college-basketball/team/schedule/_/id/85",
            "text": "Schedule"
          }
        ],
        "logo": "https://a.espncdn.com/i/teamlogos/ncaa/500/85.png"
      },
      "leaders": []
    }
  ],
  "broadcasts": [],
  "predictor": [],
  "pickcenter": [],
  "againstTheSpread": [
    {
      "team": {
        "id": "85",
        "uid": "s:40~l:54~t:85",
        "displayName": "IUPUI Jaguars",
        "abbreviation": "IUPU",
        "links": [
          {
            "href": "http://www.espn.com/womens-college-basketball/team/_/id/85/iupui-jaguars",
            "text": "Clubhouse"
          },
          {
            "href": "http://www.espn.com/womens-college-basketball/team/schedule/_/id/85",
            "text": "Schedule"
          }
        ],
        "logo": "https://a.espncdn.com/i/teamlogos/ncaa/500/85.png"
      },
      "records": []
    },
    {
      "team": {
        "id": "2473",
        "uid": "s:40~l:54~t:2473",
        "displayName": "Oakland Golden Grizzlies",
        "abbreviation": "OAK",
        "links": [
          {
            "href": "http://www.espn.com/womens-college-basketball/team/_/id/2473/oakland-golden-grizzlies",
            "text": "Clubhouse"
          },
          {
            "href": "http://www.espn.com/womens-college-basketball/team/schedule/_/id/2473",
            "text": "Schedule"
          }
        ],
        "logo": "https://a.espncdn.com/i/teamlogos/ncaa/500/2473.png"
      },
      "records": []
    }
  ],
  "odds": [],
  "winprobability": {},
  "header": {
    "id": "270642473",
    "uid": "s:40~l:54~e:270642473",
    "season": {
      "year": 2007,
      "type": 2
    },
    "timeValid": true,
    "competitions": [
      {
        "id": "270642473",
        "uid": "s:40~l:54~e:270642473~c:270642473",
        "date": "2007-03-05T18:00Z",
        "neutralSite": false,
        "conferenceCompetition": true,
        "boxscoreAvailable": false,
        "commentaryAvailable": false,
        "liveAvailable": false,
        "shotChartAvailable": false,
        "timeoutsAvailable": false,
        "possessionArrowAvailable": false,
        "onWatchESPN": false,
        "recent": false,
        "boxscoreSource": "full",
        "playByPlaySource": "none",
        "competitors": [
          {
            "id": "2473",
            "uid": "s:40~l:54~t:2473",
            "order": 0,
            "homeAway": "home",
            "winner": true,
            "team": {
              "id": "2473",
              "uid": "s:40~l:54~t:2473",
              "location": "Oakland",
              "name": "Golden Grizzlies",
              "nickname": "Oakland",
              "abbreviation": "OAK",
              "displayName": "Oakland Golden Grizzlies",
              "color": "04091c",
              "alternateColor": "bc955c",
              "logos": [
                {
                  "href": "https://a.espncdn.com/i/teamlogos/ncaa/500/2473.png",
                  "width": 500,
                  "height": 500,
                  "alt": "",
                  "rel": [
                    "full",
                    "default"
                  ],
                  "lastUpdated": "2021-08-10T19:28Z"
                },
                {
                  "href": "https://a.espncdn.com/i/teamlogos/ncaa/500-dark/2473.png",
                  "width": 500,
                  "height": 500,
                  "alt": "",
                  "rel": [
                    "full",
                    "dark"
                  ],
                  "lastUpdated": "2021-08-10T19:30Z"
                }
              ],
              "links": [
                {
                  "rel": [
                    "clubhouse",
                    "desktop",
                    "team"
                  ],
                  "href": "http://www.espn.com/womens-college-basketball/team/_/id/2473/oakland-golden-grizzlies",
                  "text": "Clubhouse"
                }
              ]
            },
            "score": "75",
            "linescores": [
              {
                "displayValue": "36"
              },
              {
                "displayValue": "39"
              }
            ],
            "record": [
              {
                "type": "total",
                "summary": "19-11",
                "displayValue": "19-11"
              },
              {
                "type": "home",
                "summary": "11-4",
                "displayValue": "11-4"
              },
              {
                "type": "vsconf",
                "summary": "12-2",
                "displayValue": "12-2"
              }
            ],
            "possession": false
          },
          {
            "id": "85",
            "uid": "s:40~l:54~t:85",
            "order": 1,
            "homeAway": "away",
            "winner": false,
            "team": {
              "id": "85",
              "uid": "s:40~l:54~t:85",
              "location": "IUPUI",
              "name": "Jaguars",
              "nickname": "IUPUI",
              "abbreviation": "IUPU",
              "displayName": "IUPUI Jaguars",
              "color": "A81F30",
              "alternateColor": "d59f0f",
              "logos": [
                {
                  "href": "https://a.espncdn.com/i/teamlogos/ncaa/500/85.png",
                  "width": 500,
                  "height": 500,
                  "alt": "",
                  "rel": [
                    "full",
                    "default"
                  ],
                  "lastUpdated": "2018-11-19T16:22Z"
                },
                {
                  "href": "https://a.espncdn.com/i/teamlogos/ncaa/500-dark/85.png",
                  "width": 500,
                  "height": 500,
                  "alt": "",
                  "rel": [
                    "full",
                    "dark"
                  ],
                  "lastUpdated": "2018-11-19T16:22Z"
                }
              ],
              "links": [
                {
                  "rel": [
                    "clubhouse",
                    "desktop",
                    "team"
                  ],
                  "href": "http://www.espn.com/womens-college-basketball/team/_/id/85/iupui-jaguars",
                  "text": "Clubhouse"
                }
              ]
            },
            "score": "60",
            "linescores": [
              {
                "displayValue": "20"
              },
              {
                "displayValue": "40"
              }
            ],
            "record": [
              {
                "type": "total",
                "summary": "14-16",
                "displayValue": "14-16"
              },
              {
                "type": "road",
                "summary": "5-11",
                "displayValue": "5-11"
              },
              {
                "type": "vsconf",
                "summary": "7-7",
                "displayValue": "7-7"
              }
            ],
            "possession": false
          }
        ],
        "status": {
          "type": {
            "id": "3",
            "name": "STATUS_FINAL",
            "state": "post",
            "completed": true,
            "description": "Final",
            "detail": "Final",
            "shortDetail": "Final"
          }
        },
        "broadcasts": []
      }
    ],
    "links": [
      {
        "rel": [
          "summary",
          "desktop",
          "event"
        ],
        "href": "http://www.espn.com/womens-college-basketball/game/_/gameId/270642473",
        "text": "Gamecast",
        "shortText": "Summary",
        "isExternal": false,
        "isPremium": false
      }
    ],
    "week": 18,
    "league": {
      "id": "54",
      "uid": "s:40~l:54",
      "name": "NCAA Women's Basketball",
      "abbreviation": "NCAAW",
      "midsizeName": "NCAAW Basketball",
      "slug": "womens-college-basketball",
      "isTournament": false,
      "links": [
        {
          "rel": [
            "index",
            "desktop",
            "league"
          ],
          "href": "https://www.espn.com/womens-college-basketball/",
          "text": "Index"
        },
        {
          "rel": [
            "index",
            "sportscenter",
            "app",
            "league"
          ],
          "href": "sportscenter://x-callback-url/showClubhouse?uid=s:40~l:54",
          "text": "Index"
        },
        {
          "rel": [
            "schedule",
            "desktop",
            "league"
          ],
          "href": "https://www.espn.com/womens-college-basketball/schedule",
          "text": "Schedule"
        },
        {
          "rel": [
            "schedule",
            "sportscenter",
            "app",
            "league"
          ],
          "href": "sportscenter://x-callback-url/showClubhouse?uid=s:40~l:54&section=scores",
          "text": "Schedule"
        },
        {
          "rel": [
            "standings",
            "desktop",
            "league"
          ],
          "href": "http://www.espn.com/womens-college-basketball/standings",
          "text": "Standings"
        },
        {
          "rel": [
            "standings",
            "sportscenter",
            "app",
            "league"
          ],
          "href": "sportscenter://x-callback-url/showClubhouse?uid=s:40~l:54&section=standings",
          "text": "Standings"
        },
        {
          "rel": [
            "rankings",
            "desktop",
            "league"
          ],
          "href": "https://www.espn.com/womens-college-basketball/rankings",
          "text": "Rankings"
        },
        {
          "rel": [
            "scores",
            "desktop",
            "league"
          ],
          "href": "http://www.espn.com/womens-college-basketball/scoreboard",
          "text": "Scores"
        },
        {
          "rel": [
            "scores",
            "sportscenter",
            "app",
            "league"
          ],
          "href": "sportscenter://x-callback-url/showClubhouse?uid=s:40~l:54&section=scores",
          "text": "Scores"
        },
        {
          "rel": [
            "stats",
            "desktop",
            "league"
          ],
          "href": "http://www.espn.com/womens-college-basketball/statistics",
          "text": "Stats"
        },
        {
          "rel": [
            "teams",
            "desktop",
            "league"
          ],
          "href": "http://www.espn.com/womens-college-basketball/teams",
          "text": "Teams"
        },
        {
          "rel": [
            "athletes",
            "desktop",
            "league"
          ],
          "href": "http://www.espn.com/womens-college-basketball/players",
          "text": "Players"
        },
        {
          "rel": [
            "injuries",
            "desktop",
            "league"
          ],
          "href": "https://www.espn.com/womens-college-basketball/injuries",
          "text": "Injuries"
        }
      ]
    },
    "gameNote": "MID CONTINENT CONF TR IN TULSA OK"
  },
  "plays": [],
  "article": [],
  "videos": [],
  "standings": {
    "fullViewLink": {
      "text": "Full Standings",
      "href": "http://www.espn.com/womens-college-basketball/standings"
    },
    "groups": [
      {
        "standings": {
          "entries": [
            {
              "team": "IUPUI",
              "link": "http://www.espn.com/womens-college-basketball/team/_/id/85/iupui-jaguars",
              "id": "85",
              "uid": "s:40~l:54~t:85",
              "stats": [
                {
                  "id": "0",
                  "name": "Season",
                  "abbreviation": "Season",
                  "displayName": "Team Season Record",
                  "shortDisplayName": "Season",
                  "description": "Overall Record",
                  "type": "total",
                  "summary": "24-5",
                  "displayValue": "24-5"
                },
                {
                  "name": "gamesBehind",
                  "displayName": "Games Back",
                  "shortDisplayName": "GB",
                  "description": "Games Back",
                  "abbreviation": "GB",
                  "type": "vsconf_gamesbehind",
                  "value": 0.0,
                  "displayValue": "-"
                },
                {
                  "id": "9",
                  "name": "vs Conference",
                  "abbreviation": "VS CONF",
                  "displayName": "CONF",
                  "shortDisplayName": "CONF",
                  "description": "Conference Record",
                  "type": "vsconf",
                  "summary": "18-4",
                  "displayValue": "18-4"
                }
              ],
              "logo": [
                {
                  "href": "https://a.espncdn.com/i/teamlogos/ncaa/500/85.png",
                  "width": 500,
                  "height": 500,
                  "alt": "",
                  "rel": [
                    "full",
                    "default"
                  ],
                  "lastUpdated": "2018-11-19T16:22Z"
                }
              ]
            },
            {
              "team": "Youngstown State",
              "link": "http://www.espn.com/womens-college-basketball/team/_/id/2754/youngstown-state-penguins",
              "id": "2754",
              "uid": "s:40~l:54~t:2754",
              "stats": [
                {
                  "id": "0",
                  "name": "Season",
                  "abbreviation": "Season",
                  "displayName": "Team Season Record",
                  "shortDisplayName": "Season",
                  "description": "Overall Record",
                  "type": "total",
                  "summary": "23-7",
                  "displayValue": "23-7"
                },
                {
                  "name": "gamesBehind",
                  "displayName": "Games Back",
                  "shortDisplayName": "GB",
                  "description": "Games Back",
                  "abbreviation": "GB",
                  "type": "vsconf_gamesbehind",
                  "value": 0.0,
                  "displayValue": "-"
                },
                {
                  "id": "9",
                  "name": "vs Conference",
                  "abbreviation": "VS CONF",
                  "displayName": "CONF",
                  "shortDisplayName": "CONF",
                  "description": "Conference Record",
                  "type": "vsconf",
                  "summary": "18-4",
                  "displayValue": "18-4"
                }
              ],
              "logo": [
                {
                  "href": "https://a.espncdn.com/i/teamlogos/ncaa/500/2754.png",
                  "width": 500,
                  "height": 500,
                  "alt": "",
                  "rel": [
                    "full",
                    "default"
                  ],
                  "lastUpdated": "2018-06-05T12:08Z"
                }
              ]
            },
            {
              "team": "Green Bay",
              "link": "http://www.espn.com/womens-college-basketball/team/_/id/2739/green-bay-phoenix",
              "id": "2739",
              "uid": "s:40~l:54~t:2739",
              "stats": [
                {
                  "id": "0",
                  "name": "Season",
                  "abbreviation": "Season",
                  "displayName": "Team Season Record",
                  "shortDisplayName": "Season",
                  "description": "Overall Record",
                  "type": "total",
                  "summary": "19-8",
                  "displayValue": "19-8"
                },
                {
                  "name": "gamesBehind",
                  "displayName": "Games Back",
                  "shortDisplayName": "GB",
                  "description": "Games Back",
                  "abbreviation": "GB",
                  "type": "vsconf_gamesbehind",
                  "value": 1.5,
                  "displayValue": "1.5"
                },
                {
                  "id": "9",
                  "name": "vs Conference",
                  "abbreviation": "VS CONF",
                  "displayName": "CONF",
                  "shortDisplayName": "CONF",
                  "description": "Conference Record",
                  "type": "vsconf",
                  "summary": "15-4",
                  "displayValue": "15-4"
                }
              ],
              "logo": [
                {
                  "href": "https://a.espncdn.com/i/teamlogos/ncaa/500/2739.png",
                  "width": 500,
                  "height": 500,
                  "alt": "",
                  "rel": [
                    "full",
                    "default"
                  ],
                  "lastUpdated": "2018-10-05T20:56Z"
                }
              ]
            },
            {
              "team": "Northern Kentucky",
              "link": "http://www.espn.com/womens-college-basketball/team/_/id/94/northern-kentucky-norse",
              "id": "94",
              "uid": "s:40~l:54~t:94",
              "stats": [
                {
                  "id": "0",
                  "name": "Season",
                  "abbreviation": "Season",
                  "displayName": "Team Season Record",
                  "shortDisplayName": "Season",
                  "description": "Overall Record",
                  "type": "total",
                  "summary": "21-8",
                  "displayValue": "21-8"
                },
                {
                  "name": "gamesBehind",
                  "displayName": "Games Back",
                  "shortDisplayName": "GB",
                  "description": "Games Back",
                  "abbreviation": "GB",
                  "type": "vsconf_gamesbehind",
                  "value": 3.0,
                  "displayValue": "3"
                },
                {
                  "id": "9",
                  "name": "vs Conference",
                  "abbreviation": "VS CONF",
                  "displayName": "CONF",
                  "shortDisplayName": "CONF",
                  "description": "Conference Record",
                  "type": "vsconf",
                  "summary": "14-6",
                  "displayValue": "14-6"
                }
              ],
              "logo": [
                {
                  "href": "https://a.espncdn.com/i/teamlogos/ncaa/500/94.png",
                  "width": 500,
                  "height": 500,
                  "alt": "",
                  "rel": [
                    "full",
                    "default"
                  ],
                  "lastUpdated": "2018-06-05T12:08Z"
                }
              ]
            },
            {
              "team": "Cleveland State",
              "link": "http://www.espn.com/womens-college-basketball/team/_/id/325/cleveland-state-vikings",
              "id": "325",
              "uid": "s:40~l:54~t:325",
              "stats": [
                {
                  "id": "0",
                  "name": "Season",
                  "abbreviation": "Season",
                  "displayName": "Team Season Record",
                  "shortDisplayName": "Season",
                  "description": "Overall Record",
                  "type": "total",
                  "summary": "21-9",
                  "displayValue": "21-9"
                },
                {
                  "name": "gamesBehind",
                  "displayName": "Games Back",
                  "shortDisplayName": "GB",
                  "description": "Games Back",
                  "abbreviation": "GB",
                  "type": "vsconf_gamesbehind",
                  "value": 3.0,
                  "displayValue": "3"
                },
                {
                  "id": "9",
                  "name": "vs Conference",
                  "abbreviation": "VS CONF",
                  "displayName": "CONF",
                  "shortDisplayName": "CONF",
                  "description": "Conference Record",
                  "type": "vsconf",
                  "summary": "14-6",
                  "displayValue": "14-6"
                }
              ],
              "logo": [
                {
                  "href": "https://a.espncdn.com/i/teamlogos/ncaa/500/325.png",
                  "width": 500,
                  "height": 500,
                  "alt": "",
                  "rel": [
                    "full",
                    "default"
                  ],
                  "lastUpdated": "2018-06-05T12:08Z"
                }
              ]
            },
            {
              "team": "Milwaukee",
              "link": "http://www.espn.com/womens-college-basketball/team/_/id/270/milwaukee-panthers",
              "id": "270",
              "uid": "s:40~l:54~t:270",
              "stats": [
                {
                  "id": "0",
                  "name": "Season",
                  "abbreviation": "Season",
                  "displayName": "Team Season Record",
                  "shortDisplayName": "Season",
                  "description": "Overall Record",
                  "type": "total",
                  "summary": "14-16",
                  "displayValue": "14-16"
                },
                {
                  "name": "gamesBehind",
                  "displayName": "Games Back",
                  "shortDisplayName": "GB",
                  "description": "Games Back",
                  "abbreviation": "GB",
                  "type": "vsconf_gamesbehind",
                  "value": 5.0,
                  "displayValue": "5"
                },
                {
                  "id": "9",
                  "name": "vs Conference",
                  "abbreviation": "VS CONF",
                  "displayName": "CONF",
                  "shortDisplayName": "CONF",
                  "description": "Conference Record",
                  "type": "vsconf",
                  "summary": "13-9",
                  "displayValue": "13-9"
                }
              ],
              "logo": [
                {
                  "href": "https://a.espncdn.com/i/teamlogos/ncaa/500/270.png",
                  "width": 500,
                  "height": 500,
                  "alt": "",
                  "rel": [
                    "full",
                    "default"
                  ],
                  "lastUpdated": "2019-12-17T15:38Z"
                }
              ]
            },
            {
              "team": "Oakland",
              "link": "http://www.espn.com/womens-college-basketball/team/_/id/2473/oakland-golden-grizzlies",
              "id": "2473",
              "uid": "s:40~l:54~t:2473",
              "stats": [
                {
                  "id": "0",
                  "name": "Season",
                  "abbreviation": "Season",
                  "displayName": "Team Season Record",
                  "shortDisplayName": "Season",
                  "description": "Overall Record",
                  "type": "total",
                  "summary": "15-15",
                  "displayValue": "15-15"
                },
                {
                  "name": "gamesBehind",
                  "displayName": "Games Back",
                  "shortDisplayName": "GB",
                  "description": "Games Back",
                  "abbreviation": "GB",
                  "type": "vsconf_gamesbehind",
                  "value": 6.0,
                  "displayValue": "6"
                },
                {
                  "id": "9",
                  "name": "vs Conference",
                  "abbreviation": "VS CONF",
                  "displayName": "CONF",
                  "shortDisplayName": "CONF",
                  "description": "Conference Record",
                  "type": "vsconf",
                  "summary": "11-9",
                  "displayValue": "11-9"
                }
              ],
              "logo": [
                {
                  "href": "https://a.espncdn.com/i/teamlogos/ncaa/500/2473.png",
                  "width": 500,
                  "height": 500,
                  "alt": "",
                  "rel": [
                    "full",
                    "default"
                  ],
                  "lastUpdated": "2021-08-10T19:28Z"
                }
              ]
            },
            {
              "team": "Robert Morris",
              "link": "http://www.espn.com/womens-college-basketball/team/_/id/2523/robert-morris-colonials",
              "id": "2523",
              "uid": "s:40~l:54~t:2523",
              "stats": [
                {
                  "id": "0",
                  "name": "Season",
                  "abbreviation": "Season",
                  "displayName": "Team Season Record",
                  "shortDisplayName": "Season",
                  "description": "Overall Record",
                  "type": "total",
                  "summary": "13-15",
                  "displayValue": "13-15"
                },
                {
                  "name": "gamesBehind",
                  "displayName": "Games Back",
                  "shortDisplayName": "GB",
                  "description": "Games Back",
                  "abbreviation": "GB",
                  "type": "vsconf_gamesbehind",
                  "value": 7.0,
                  "displayValue": "7"
                },
                {
                  "id": "9",
                  "name": "vs Conference",
                  "abbreviation": "VS CONF",
                  "displayName": "CONF",
                  "shortDisplayName": "CONF",
                  "description": "Conference Record",
                  "type": "vsconf",
                  "summary": "11-11",
                  "displayValue": "11-11"
                }
              ],
              "logo": [
                {
                  "href": "https://a.espncdn.com/i/teamlogos/ncaa/500/2523.png",
                  "width": 500,
                  "height": 500,
                  "alt": "",
                  "rel": [
                    "full",
                    "default"
                  ],
                  "lastUpdated": "2020-12-16T15:18Z"
                }
              ]
            },
            {
              "team": "Purdue Fort Wayne",
              "link": "http://www.espn.com/womens-college-basketball/team/_/id/2870/purdue-fort-wayne-mastodons",
              "id": "2870",
              "uid": "s:40~l:54~t:2870",
              "stats": [
                {
                  "id": "0",
                  "name": "Season",
                  "abbreviation": "Season",
                  "displayName": "Team Season Record",
                  "shortDisplayName": "Season",
                  "description": "Overall Record",
                  "type": "total",
                  "summary": "7-21",
                  "displayValue": "7-21"
                },
                {
                  "name": "gamesBehind",
                  "displayName": "Games Back",
                  "shortDisplayName": "GB",
                  "description": "Games Back",
                  "abbreviation": "GB",
                  "type": "vsconf_gamesbehind",
                  "value": 10.5,
                  "displayValue": "10.5"
                },
                {
                  "id": "9",
                  "name": "vs Conference",
                  "abbreviation": "VS CONF",
                  "displayName": "CONF",
                  "shortDisplayName": "CONF",
                  "description": "Conference Record",
                  "type": "vsconf",
                  "summary": "7-14",
                  "displayValue": "7-14"
                }
              ],
              "logo": [
                {
                  "href": "https://a.espncdn.com/i/teamlogos/ncaa/500/2870.png",
                  "width": 500,
                  "height": 500,
                  "alt": "",
                  "rel": [
                    "full",
                    "default"
                  ],
                  "lastUpdated": "2018-10-30T18:14Z"
                }
              ]
            },
            {
              "team": "Wright State",
              "link": "http://www.espn.com/womens-college-basketball/team/_/id/2750/wright-state-raiders",
              "id": "2750",
              "uid": "s:40~l:54~t:2750",
              "stats": [
                {
                  "id": "0",
                  "name": "Season",
                  "abbreviation": "Season",
                  "displayName": "Team Season Record",
                  "shortDisplayName": "Season",
                  "description": "Overall Record",
                  "type": "total",
                  "summary": "4-19",
                  "displayValue": "4-19"
                },
                {
                  "name": "gamesBehind",
                  "displayName": "Games Back",
                  "shortDisplayName": "GB",
                  "description": "Games Back",
                  "abbreviation": "GB",
                  "type": "vsconf_gamesbehind",
                  "value": 14.5,
                  "displayValue": "14.5"
                },
                {
                  "id": "9",
                  "name": "vs Conference",
                  "abbreviation": "VS CONF",
                  "displayName": "CONF",
                  "shortDisplayName": "CONF",
                  "description": "Conference Record",
                  "type": "vsconf",
                  "summary": "3-18",
                  "displayValue": "3-18"
                }
              ],
              "logo": [
                {
                  "href": "https://a.espncdn.com/i/teamlogos/ncaa/500/2750.png",
                  "width": 500,
                  "height": 500,
                  "alt": "",
                  "rel": [
                    "full",
                    "default"
                  ],
                  "lastUpdated": "2018-06-05T12:08Z"
                }
              ]
            },
            {
              "team": "UIC",
              "link": "http://www.espn.com/womens-college-basketball/team/_/id/82/uic-flames",
              "id": "82",
              "uid": "s:40~l:54~t:82",
              "stats": [
                {
                  "id": "0",
                  "name": "Season",
                  "abbreviation": "Season",
                  "displayName": "Team Season Record",
                  "shortDisplayName": "Season",
                  "description": "Overall Record",
                  "type": "total",
                  "summary": "2-25",
                  "displayValue": "2-25"
                },
                {
                  "name": "gamesBehind",
                  "displayName": "Games Back",
                  "shortDisplayName": "GB",
                  "description": "Games Back",
                  "abbreviation": "GB",
                  "type": "vsconf_gamesbehind",
                  "value": 15.5,
                  "displayValue": "15.5"
                },
                {
                  "id": "9",
                  "name": "vs Conference",
                  "abbreviation": "VS CONF",
                  "displayName": "CONF",
                  "shortDisplayName": "CONF",
                  "description": "Conference Record",
                  "type": "vsconf",
                  "summary": "1-20",
                  "displayValue": "1-20"
                }
              ],
              "logo": [
                {
                  "href": "https://a.espncdn.com/i/teamlogos/ncaa/500/82.png",
                  "width": 500,
                  "height": 500,
                  "alt": "",
                  "rel": [
                    "full",
                    "default"
                  ],
                  "lastUpdated": "2021-08-10T21:50Z"
                }
              ]
            },
            {
              "team": "Detroit Mercy",
              "link": "http://www.espn.com/womens-college-basketball/team/_/id/2174/detroit-mercy-titans",
              "id": "2174",
              "uid": "s:40~l:54~t:2174",
              "stats": [
                {
                  "id": "0",
                  "name": "Season",
                  "abbreviation": "Season",
                  "displayName": "Team Season Record",
                  "shortDisplayName": "Season",
                  "description": "Overall Record",
                  "type": "total",
                  "summary": "1-27",
                  "displayValue": "1-27"
                },
                {
                  "name": "gamesBehind",
                  "displayName": "Games Back",
                  "shortDisplayName": "GB",
                  "description": "Games Back",
                  "abbreviation": "GB",
                  "type": "vsconf_gamesbehind",
                  "value": 17.0,
                  "displayValue": "17"
                },
                {
                  "id": "9",
                  "name": "vs Conference",
                  "abbreviation": "VS CONF",
                  "displayName": "CONF",
                  "shortDisplayName": "CONF",
                  "description": "Conference Record",
                  "type": "vsconf",
                  "summary": "1-21",
                  "displayValue": "1-21"
                }
              ],
              "logo": [
                {
                  "href": "https://a.espncdn.com/i/teamlogos/ncaa/500/2174.png",
                  "width": 500,
                  "height": 500,
                  "alt": "",
                  "rel": [
                    "full",
                    "default"
                  ],
                  "lastUpdated": "2018-06-05T12:08Z"
                }
              ]
            }
          ]
        },
        "header": "2021-22 Horizon League Standings",
        "href": "https://www.espn.com/womens-college-basketball/standings/_/group/45"
      }
    ]
  },
  "teamInfo": {},
  "espnWP": {},
  "season": [],
  "timeouts": []
}